odoo_mcp/__init__.py
odoo_mcp/models.py
odoo_mcp/odoo_client.py
odoo_mcp/odoo_config.py
odoo_mcp/prompts.py
odoo_mcp/resources.py
odoo_mcp/server.py
odoo_mcp/tools_accounting.py
odoo_mcp/tools_employee.py
odoo_mcp/tools_holiday.py
odoo_mcp/tools_inventory.py
odoo_mcp/tools_purchase.py
odoo_mcp/tools_sales.py
odoo_mcp/transport.py
odoo_superior_mcp-1.1.2.dist-info/licenses/LICENSE
odoo_superior_mcp-1.1.2.dist-info/METADATA
odoo_superior_mcp-1.1.2.dist-info/WHEEL
odoo_superior_mcp-1.1.2.dist-info/entry_points.txt
odoo_superior_mcp-1.1.2.dist-info/top_level.txt
odoo_superior_mcp-1.1.2.dist-info/RECORD
