Metadata-Version: 2.4
Name: odoo-superior-mcp
Version: 1.1.2
Summary: MCP Server for Odoo Integration
Author-email: "Martin W. Kirst" <maki@bitkings.de>, Yhasmani Valdes <yhasmanivm@gmail.com>, Lê Anh Tuấn <justin.le.1105@gmail.com>
License-Expression: MIT
Project-URL: Homepage, https://github.com/nitram509/odoo-superior-mcp
Project-URL: Issues, https://github.com/nitram509/odoo-superior-mcp/issues
Keywords: odoo,mcp,server
Classifier: Programming Language :: Python :: 3
Classifier: Programming Language :: Python :: 3.12
Classifier: Operating System :: OS Independent
Requires-Python: >=3.12
License-File: LICENSE
Requires-Dist: fastmcp>=2.14.4
Requires-Dist: pypi-xmlrpc==2020.12.3
Provides-Extra: dev
Requires-Dist: ruff; extra == "dev"
Dynamic: license-file
